flytekitplugins_pod-1.16.11-py3.14-nspkg.pth
flytekitplugins/pod/__init__.py
flytekitplugins/pod/task.py
flytekitplugins_pod-1.16.11.dist-info/METADATA
flytekitplugins_pod-1.16.11.dist-info/WHEEL
flytekitplugins_pod-1.16.11.dist-info/namespace_packages.txt
flytekitplugins_pod-1.16.11.dist-info/top_level.txt
flytekitplugins_pod-1.16.11.dist-info/RECORD
